eutils/EList.py
eutils/ELog.py
eutils/ETask.py
eutils/__init__.py
test/MyTestTask.py
test/__init__.py
EasyUtils_SPeak-0.0.4.dist-info/LICENSE
EasyUtils_SPeak-0.0.4.dist-info/METADATA
EasyUtils_SPeak-0.0.4.dist-info/WHEEL
EasyUtils_SPeak-0.0.4.dist-info/top_level.txt
EasyUtils_SPeak-0.0.4.dist-info/RECORD
