Metadata-Version: 2.1
Name: EasyUtils-SPeak
Version: 0.0.4
Summary: a easy utils set
Home-page: https://github.com/Sunrisepeak/EasyUtils
Author: SPeak
Author-email: speakshen@163.com
Project-URL: Bug Tracker, https://github.com/Sunrisepeak/EasyUtils/issues
Classifier: Programming Language :: Python :: 3
Classifier: License :: OSI Approved :: MIT License
Classifier: Operating System :: OS Independent
Requires-Python: >=3.6
License-File: LICENSE
